mesa/__init__.py
mesa/agent.py
mesa/batchrunner.py
mesa/datacollection.py
mesa/main.py
mesa/model.py
mesa/space.py
mesa/time.py
mesa/cookiecutter-mesa/cookiecutter.json
mesa/visualization/ModularVisualization.py
mesa/visualization/TextVisualization.py
mesa/visualization/UserParam.py
mesa/visualization/__init__.py
mesa/visualization/modules/BarChartVisualization.py
mesa/visualization/modules/CanvasGridVisualization.py
mesa/visualization/modules/ChartVisualization.py
mesa/visualization/modules/HexGridVisualization.py
mesa/visualization/modules/NetworkVisualization.py
mesa/visualization/modules/PieChartVisualization.py
mesa/visualization/modules/TextVisualization.py
mesa/visualization/modules/__init__.py
mesa/visualization/templates/modular_template.html
mesa/visualization/templates/css/bootstrap-slider.css
mesa/visualization/templates/css/bootstrap-slider.min.css
mesa/visualization/templates/css/bootstrap-switch.css
mesa/visualization/templates/css/bootstrap-switch.min.css
mesa/visualization/templates/css/bootstrap-theme.css
mesa/visualization/templates/css/bootstrap-theme.css.map
mesa/visualization/templates/css/bootstrap-theme.min.css
mesa/visualization/templates/css/bootstrap-theme.min.css.map
mesa/visualization/templates/css/bootstrap.css
mesa/visualization/templates/css/bootstrap.css.map
mesa/visualization/templates/css/bootstrap.min.css
mesa/visualization/templates/css/bootstrap.min.css.map
mesa/visualization/templates/css/visualization.css
mesa/visualization/templates/fonts/glyphicons-halflings-regular.eot
mesa/visualization/templates/fonts/glyphicons-halflings-regular.svg
mesa/visualization/templates/fonts/glyphicons-halflings-regular.ttf
mesa/visualization/templates/fonts/glyphicons-halflings-regular.woff
mesa/visualization/templates/fonts/glyphicons-halflings-regular.woff2
mesa/visualization/templates/js/BarChartModule.js
mesa/visualization/templates/js/CanvasHexModule.js
mesa/visualization/templates/js/CanvasModule.js
Mesa_Adapted-0.8.7.3.dist-info/LICENSE
Mesa_Adapted-0.8.7.3.dist-info/METADATA
Mesa_Adapted-0.8.7.3.dist-info/WHEEL
Mesa_Adapted-0.8.7.3.dist-info/entry_points.txt
Mesa_Adapted-0.8.7.3.dist-info/top_level.txt
Mesa_Adapted-0.8.7.3.dist-info/RECORD
