Metadata-Version: 2.1
Name: Mesa-Adapted
Version: 0.8.7.3
Summary: Forked Agent-based modeling (ABM) in Python 3+
Home-page: https://github.com/senden9/mesa/tree/pipy-fork
Author: Project Mesa Team / Stefano Probst
Author-email: senden9@gmail.com
License: Apache 2.0
Keywords: agent based modeling model ABM simulation multi-agent
Platform: UNKNOWN
Classifier: Topic :: Scientific/Engineering
Classifier: Topic :: Scientific/Engineering :: Artificial Life
Classifier: Topic :: Scientific/Engineering :: Artificial Intelligence
Classifier: Intended Audience :: Science/Research
Classifier: Programming Language :: Python :: 3 :: Only
Classifier: License :: OSI Approved :: Apache Software License
Classifier: Operating System :: OS Independent
Classifier: Development Status :: 3 - Alpha
Classifier: Natural Language :: English
Requires-Dist: click
Requires-Dist: cookiecutter
Requires-Dist: networkx
Requires-Dist: numpy
Requires-Dist: pandas
Requires-Dist: tornado
Requires-Dist: tqdm
Provides-Extra: dev
Requires-Dist: coverage ; extra == 'dev'
Requires-Dist: flake8 ; extra == 'dev'
Requires-Dist: pytest (>=4.6) ; extra == 'dev'
Requires-Dist: pytest-cov ; extra == 'dev'
Requires-Dist: sphinx ; extra == 'dev'
Provides-Extra: docs
Requires-Dist: sphinx ; extra == 'docs'
Requires-Dist: ipython ; extra == 'docs'
